aboutcode/__init__.py
aboutcode/federatedcode/__init__.py
aboutcode/federatedcode/cli.py
aboutcode/federatedcode/client/__init__.py
aboutcode/federatedcode/contrib/__init__.py
aboutcode/federatedcode/contrib/django/__init__.py
aboutcode/federatedcode/contrib/django/models.py
aboutcode/federatedcode/contrib/django/utils.py
fedcode/__init__.py
fedcode/activitypub.py
fedcode/admin.py
fedcode/apps.py
fedcode/forms.py
fedcode/middleware.py
fedcode/models.py
fedcode/schemas.py
fedcode/signatures.py
fedcode/utils.py
fedcode/views.py
fedcode/migrations/0001_initial.py
fedcode/migrations/0002_alter_package_options_alter_federaterequest_done_and_more.py
fedcode/migrations/0003_remove_package_local_remove_person_local_and_more.py
fedcode/migrations/0004_alter_vulnerability_unique_together.py
fedcode/migrations/0005_remove_person_avatar.py
fedcode/migrations/__init__.py
fedcode/pipelines/__init__.py
fedcode/pipelines/sync_scancode_scans.py
fedcode/pipelines/sync_vulnerablecode.py
fedcode/templatetags/__init__.py
fedcode/templatetags/webfinger_image.py
federatedcode/__init__.py
federatedcode/asgi.py
federatedcode/context_processors.py
federatedcode/settings.py
federatedcode/urls.py
federatedcode/wsgi.py
federatedcode-0.1.0.dist-info/AUTHORS.rst
federatedcode-0.1.0.dist-info/CHANGELOG.rst
federatedcode-0.1.0.dist-info/CODE_OF_CONDUCT.rst
federatedcode-0.1.0.dist-info/METADATA
federatedcode-0.1.0.dist-info/NOTICE
federatedcode-0.1.0.dist-info/WHEEL
federatedcode-0.1.0.dist-info/apache-2.0.LICENSE
federatedcode-0.1.0.dist-info/entry_points.txt
federatedcode-0.1.0.dist-info/top_level.txt
federatedcode-0.1.0.dist-info/RECORD
