Metadata-Version: 2.1
Name: federatedcode
Version: 0.1.0
Summary: Share software metadata and vulnerabilities in a federated manner over ActivityPub and git
Home-page: https://github.com/nexB/federatedcode
Author: nexB Inc., AboutCode.org  and others
Author-email: info@aboutcode.org
License: Apache-2.0
Keywords: open source,package,dependency,activitypub,vulnerabilities,security,dependencies,packages
Classifier: Development Status :: 5 - Production/Stable
Classifier: Intended Audience :: Developers
Classifier: Programming Language :: Python :: 3
Classifier: Programming Language :: Python :: 3 :: Only
Classifier: Topic :: Software Development
Classifier: Topic :: Utilities
Requires-Python: >=3.10
License-File: apache-2.0.LICENSE
License-File: NOTICE
License-File: AUTHORS.rst
License-File: CHANGELOG.rst
License-File: CODE_OF_CONDUCT.rst
Requires-Dist: Django==5.1.2
Requires-Dist: django-oauth-toolkit==3.0.1
Requires-Dist: djangorestframework==3.15.2
Requires-Dist: django-environ==0.11.2
Requires-Dist: gunicorn==23.0.0
Requires-Dist: GitPython==3.1.43
Requires-Dist: requests==2.32.3
Requires-Dist: httpx==0.28.1
Requires-Dist: http-message-signatures==0.5.0
Requires-Dist: attrs==24.2.0
Requires-Dist: pillow==11.0.0
Requires-Dist: cryptography==44.0.0
Requires-Dist: idna==3.10
Requires-Dist: packageurl-python==0.16.0
Requires-Dist: psycopg2-binary==2.9.10
Requires-Dist: pytest==8.3.4
Requires-Dist: pytest-django==4.9.0
Requires-Dist: saneyaml==0.6.1
Requires-Dist: django-ninja==1.3.0
Requires-Dist: pydantic==2.10.3
Requires-Dist: aboutcode.pipeline==0.2.0
Requires-Dist: aboutcode.hashid==0.2.0
Requires-Dist: python-dotenv==1.0.1
Requires-Dist: click==8.1.7
Provides-Extra: dev
Requires-Dist: flake8>=6.1.0; extra == "dev"
Requires-Dist: black>=23.0.0; extra == "dev"
Requires-Dist: isort>=5.12.0; extra == "dev"
Requires-Dist: doc8>=0.11.2; extra == "dev"
Requires-Dist: pydocstyle>=6.3.0; extra == "dev"
Requires-Dist: bandit>=1.7.5; extra == "dev"
Requires-Dist: pytest!=7.0.0,>=6; extra == "dev"
Requires-Dist: pytest-xdist>=2; extra == "dev"
Requires-Dist: twine>=6.0.1; extra == "dev"
Requires-Dist: flot>=0.7.2; extra == "dev"
Requires-Dist: django-debug-toolbar==4.2.0; extra == "dev"
Provides-Extra: docs
Requires-Dist: Sphinx>=5.0.2; extra == "docs"
Requires-Dist: sphinx-rtd-theme>=1.0.0; extra == "docs"
Requires-Dist: sphinx-reredirects>=0.1.2; extra == "docs"
Requires-Dist: doc8>=0.11.2; extra == "docs"
Requires-Dist: sphinx-autobuild; extra == "docs"
Requires-Dist: sphinx-rtd-dark-mode>=1.3.0; extra == "docs"
Requires-Dist: sphinx-copybutton; extra == "docs"
Requires-Dist: sphinx-autobuild>=2021.3.14; extra == "docs"
Requires-Dist: sphinxcontrib_django; extra == "docs"
Requires-Dist: sphinx-jsonschema; extra == "docs"
